aqicalc/__init__.py
aqicalc/constants.py
aqicalc/algos/__init__.py
aqicalc/algos/base.py
aqicalc/algos/caqi.py
aqicalc/algos/cpcb.py
aqicalc/algos/epa.py
aqicalc/algos/iema.py
aqicalc/algos/kaqi.py
aqicalc/algos/mep.py
aqicalc-0.0.8.1.dist-info/LICENSE
aqicalc-0.0.8.1.dist-info/METADATA
aqicalc-0.0.8.1.dist-info/WHEEL
aqicalc-0.0.8.1.dist-info/entry_points.txt
aqicalc-0.0.8.1.dist-info/top_level.txt
aqicalc-0.0.8.1.dist-info/RECORD
